{
"type": "FeatureCollection",
"name": "airterjun",
"crs": { "type": "name", "properties": { "name": "urn:ogc:def:crs:OGC:1.3:CRS84" } },
"features": [
{ "type": "Feature", "properties": { "NAMOBJ": null, "FCODE": null, "ELEVAS": 0.0, "REMARK": "Air Terjun", "SRS_ID": null, "LCODE": "DA0060", "METADATA": null }, "geometry": { "type": "Point", "coordinates": [ 109.515972813000076, -7.440145658999938, 0.0 ] } },
{ "type": "Feature", "properties": { "NAMOBJ": null, "FCODE": null, "ELEVAS": 0.0, "REMARK": "Air Terjun", "SRS_ID": null, "LCODE": "DA0060", "METADATA": null }, "geometry": { "type": "Point", "coordinates": [ 109.525080827000068, -7.43489623399995, 0.0 ] } },
{ "type": "Feature", "properties": { "NAMOBJ": null, "FCODE": null, "ELEVAS": 0.0, "REMARK": "Air Terjun", "SRS_ID": null, "LCODE": "DA0060", "METADATA": null }, "geometry": { "type": "Point", "coordinates": [ 109.528953080000065, -7.432605601999967, 0.0 ] } },
{ "type": "Feature", "properties": { "NAMOBJ": null, "FCODE": null, "ELEVAS": 0.0, "REMARK": "Air Terjun", "SRS_ID": null, "LCODE": "DA0060", "METADATA": null }, "geometry": { "type": "Point", "coordinates": [ 109.538839521000057, -7.428136244999962, 0.0 ] } },
{ "type": "Feature", "properties": { "NAMOBJ": null, "FCODE": null, "ELEVAS": 0.0, "REMARK": "Air Terjun", "SRS_ID": null, "LCODE": "DA0060", "METADATA": null }, "geometry": { "type": "Point", "coordinates": [ 109.544615678000071, -7.425906078999958, 0.0 ] } },
{ "type": "Feature", "properties": { "NAMOBJ": null, "FCODE": null, "ELEVAS": 0.0, "REMARK": "Air Terjun", "SRS_ID": null, "LCODE": "DA0060", "METADATA": null }, "geometry": { "type": "Point", "coordinates": [ 109.568378901000074, -7.405113563999976, 0.0 ] } }
]
}
